{
  "HOSPITAL_001": {
    "location_code": "HOSPITAL_001",
    "location_name": "医院",
    "description": "林先生被确诊早发性阿尔茨海默病的地方。",
    "detail": "医院附近是热闹的街道，雨帘中车辆行人穿梭，法国梧桐静默矗立，一切都雾蒙蒙的，像颜色很淡的印象派油画，营造出一种忧郁而真实的氛围。",
    "source": "user_1_天才基本法_3"
  },
  "NOODLE_SHOP_001": {
    "location_code": "NOODLE_SHOP_001",
    "location_name": "打卤面店",
    "description": "位于医院附近的一家面店，林朝夕和她父亲在确诊后在这里用餐。",
    "detail": "恰逢中午雨天，店内水汽充盈，热气腾腾，是父女二人讨论病情和人生哲理的场景地，充满了生活气息。",
    "source": "user_1_天才基本法_3"
  },
  "UNIV_ACTIVITY_CENTER_001": {
    "location_code": "UNIV_ACTIVITY_CENTER_001",
    "location_name": "大学生活动中心二楼",
    "description": "林朝夕回校后直接前往的地点，用于举办大学城高校联合智力竞赛的会议。",
    "detail": "作为学生社团活动的中心，这里是不同高校学生会代表聚集的地方，充满了学术交流和竞争的氛围。",
    "source": "user_1_天才基本法_3"
  },
  "MEETING_ROOM_001": {
    "location_code": "MEETING_ROOM_001",
    "location_name": "会议室",
    "description": "大学生活动中心二楼的一个房间，是大学城高校联合智力竞赛选题会议的场所。",
    "detail": "林朝夕进入时，会议室里传出吵闹的说话声，在她推开门后瞬间安静下来。这里是不同高校代表就智力题展开讨论、展现各自能力和学校实力的地方，也是林朝夕和安潇潇产生交锋的舞台。",
    "source": "user_1_天才基本法_3"
  }
}